{
  "series": "Narcos S2 E2",
  "season": "Season 1",
  "season_number": 1,
  "episode_number": 1,
  "subtitle_file": "narcos_s2_e2.srt",
  "analysis_date": "2026-03-18T21:19:02.971063",
  "thresholds": {
    "series_threshold": 2,
    "english_threshold": 123196001,
    "max_english_freq": 20000000
  },
  "word_counts": {
    "tier_1_hard_usable": 9,
    "tier_2_random": 95,
    "tier_3_common": 17,
    "tier_4_rare_in_series": 3,
    "tier_5_filtered": 373
  },
  "excluded_names_fantasy_count": 65
}